<?xml version="1.0"?>
<gconf>
	<dir name="schemas">
		<dir name="desktop">
			<dir name="gnome">
				<dir name="accessibility">
					<dir name="mouse">
						<entry name="animate_cursor">
							<local_schema short_desc="அசைவூட்ட நிலைக்காட்டி">
								<longdesc>நிலைகாட்டி மீது கடந்த நேரத்தை காட்டுக.</longdesc>
							</local_schema>
						</entry>
						<entry name="button_layout">
							<local_schema short_desc="பொத்தான் பாங்கு">
								<longdesc>சொடுக்கு வகை சாளரத்தில் பொத்தான் பாங்கு (&quot;0&quot; = உரை, &quot;1&quot;= சின்னம், &quot;2&quot;=இரண்டும்)</longdesc>
							</local_schema>
						</entry>
						<entry name="dwell_show_ctw">
							<local_schema short_desc="சொடுக்கு வகை சாளரத்தை காட்டு ">
								<longdesc>சொடுக்கு வகை சாளரத்தை காட்டு </longdesc>
							</local_schema>
						</entry>
						<entry name="dwell_mode">
							<local_schema short_desc="நிலை சொடுக்கு முறைமை">
								<longdesc>நிலை சொடுக்கு முறைமை (&quot;0&quot; = அசைவு முறைமை, &quot;1&quot; = சாளரம் முறைமை)</longdesc>
							</local_schema>
						</entry>
						<entry name="dwell_gesture_secondary">
							<local_schema short_desc="அசைவால் இரண்டாம் சொடுக்கு">
								<longdesc>இரண்டாவது சொடுக்கு செய்ய வழிகாட்டி (&quot;0&quot; = இடது, &quot;1&quot; = வலது, &quot;2&quot; = மேலே, &quot;3&quot; = கீழ்)</longdesc>
							</local_schema>
						</entry>
						<entry name="dwell_gesture_drag">
							<local_schema short_desc="அசைவால் இழுப்பு சொடுக்கு">
								<longdesc>சொடுக்கு இழுப்பு  செய்ய வழிகாட்டி (&quot;0&quot; = இடது, &quot;1&quot; = வலது, &quot;2&quot; = மேலே, &quot;3&quot; = கீழ்)</longdesc>
							</local_schema>
						</entry>
						<entry name="dwell_gesture_double">
							<local_schema short_desc="அசைவால் இரட்டிப்பு சொடுக்கு">
								<longdesc>இரட்டிப்பு சொடுக்கு செய்ய வழிகாட்டி (&quot;0&quot; = இடது, &quot;1&quot; = வலது, &quot;2&quot; = மேலே, &quot;3&quot; =கீழ்)</longdesc>
							</local_schema>
						</entry>
						<entry name="dwell_gesture_single">
							<local_schema short_desc="அசைவால் தனி சொடுக்கு">
								<longdesc>தனி சொடுக்கு செய்ய வழிகாட்டி (&quot;0&quot; = இடது, &quot;1&quot; = வலது, &quot;2&quot; = மேலே, &quot;3&quot; = கீழ்)</longdesc>
							</local_schema>
						</entry>
						<entry name="dwell_time">
							<local_schema short_desc="நிலை சொடுக்கு நேரம்">
								<longdesc>ஒரு சொடுக்கு இடரப்படும் முன் நேரம், வினாடிகளில்</longdesc>
							</local_schema>
						</entry>
						<entry name="dwell_enable">
							<local_schema short_desc="நிலை சொடுக்கு செயல்படுத்து">
								<longdesc>நிலை சொடுக்கு செயல்படுத்து</longdesc>
							</local_schema>
						</entry>
						<entry name="delay_time">
							<local_schema short_desc="இரண்டாம் சொடுக்கு நேரம்">
								<longdesc>இரண்டாம் சொடுக்கு இடரப்படும் முன் நேரம், வினாடிகளில்</longdesc>
							</local_schema>
						</entry>
						<entry name="delay_enable">
							<local_schema short_desc="இரண்டாம் சொடுக்கு செயல்படுத்து">
								<longdesc>மெய்நிகர் இரண்டாம்  சொடுக்கு செயல்படுத்து</longdesc>
							</local_schema>
						</entry>
						<entry name="threshold">
							<local_schema short_desc="அசைவுக்கு குறைந்த பட்ச வரை">
								<longdesc>அசைவு அடையாளம் காணப்பட குறைந்த பட்ச நகர்வு தொலைவு  பிக்ஸல்களில்.</longdesc>
							</local_schema>
						</entry>
					</dir>
				</dir>
			</dir>
		</dir>
		<dir name="apps">
			<entry name="disable_user_plugins">
				<local_schema short_desc="பயனரின் இல்ல அடைவில் சொருகிகளை செயல் நீக்கம் செய்ய வேண்டுமா?">
					<longdesc>பயனரின் இல்ல அடைவில் சொருகிகளை செயல் நீக்கம் செய்ய வேண்டுமா?</longdesc>
				</local_schema>
			</entry>
			<dir name="totem">
				<entry name="autoload_subtitles">
					<local_schema short_desc="திரைப்படம் ஏற்றப்படும்போது தானியங்கியாக உரை துணத்தலைப்புகளை ஏற்றுவதா">
						<longdesc>திரைப்படம் ஏற்றப்படும்போது தானியங்கியாக உரை துணத்தலைப்புகளை ஏற்றுவதா</longdesc>
					</local_schema>
				</entry>
				<entry name="screenshot_save_path">
					<local_schema short_desc="&quot;திரைவெட்டு எடு...&quot;  உரையாடல்களுக்கு முன்னிருப்பு இடம்">
						<longdesc>&quot;திரைவெட்டு எடு...&quot;  உரையாடல்களுக்கு முன்னிருப்பு இடம் முன்னிருப்பு படங்கள்  அடைவு</longdesc>
					</local_schema>
				</entry>
				<entry name="open_path">
					<local_schema short_desc="&quot;Open...&quot; (திற) உரையாடல்களுக்கு முன்னிருப்பு இடம்">
						<longdesc>&quot;Open...&quot; (திற) உரையாடல்களுக்கு முன்னிருப்பு இடம் ,முன்னிருப்பு இப்போதைய அடைவு</longdesc>
					</local_schema>
				</entry>
				<entry name="subtitle_encoding">
					<local_schema short_desc="உப தலைப்பு குறியாக்கம்">
					</local_schema>
				</entry>
				<entry name="subtitle_font">
					<local_schema short_desc="உப தலைப்பு எழுத்துரு">
						<longdesc>துணை தலைப்புகளை காட்ட பாங்கோ எழுதுரு விவரம்.</longdesc>
					</local_schema>
				</entry>
				<entry name="buffer-size">
					<local_schema short_desc="இடையக அளவு">
						<longdesc>காட்டு முன் குறி உணர்வதற்கு  அதிக அளவு தரவு (நொடிகளில்)</longdesc>
					</local_schema>
				</entry>
				<entry name="network-buffer-threshold">
					<local_schema short_desc="பிணைய இடையக விளிம்பு">
						<longdesc>வலை ஓடைகளில் ஒடையைக்காட்ட துவங்கு முன் இடைமாற்றாக சேமிக்க வேண்டிய தரவு (வினாடிகளில்)</longdesc>
					</local_schema>
				</entry>
				<entry name="volume">
					<local_schema short_desc="ஒலி அளவு">
						<longdesc>ஒலி அளவு, சத விகிதத்தில், 0 க்கும் 100 க்கும் இடையே</longdesc>
					</local_schema>
				</entry>
				<entry name="visual_quality">
					<local_schema short_desc="காட்சிக்கு தர அளவு:">
						<longdesc>ஒலி காணல்களுக்கு தர அமைப்பு: &quot;0&quot; சிறியது, &quot;1&quot; சாதாரணதுக்கு, &quot;2&quot; பெரியதுக்கு, &quot;3&quot; மிகப்பெரியதுக்கு.</longdesc>
					</local_schema>
				</entry>
				<entry name="window_on_top">
					<local_schema short_desc="முக்கிய சாளரம் எப்போதும் மேலே இருக்க வேண்டுமா?">
						<longdesc>முக்கிய சாளரம் எப்போதும் மற்றவற்றின் மேலே இருக்க வேண்டுமா?</longdesc>
					</local_schema>
				</entry>
				<entry name="audio_output_type">
					<local_schema short_desc="பயன்படுத்த ஒலி வெளியீட்டு வகை">
						<longdesc>பயன்படுத்த ஒலி வெளியீட்டு வகை: &quot;0&quot; ஸ்டீரியோவுக்கு, &quot;1&quot; 4-தட வெளியீடுக்கு &quot;2&quot; 5.0 தட வெளியீடுக்கு, &quot;3&quot; 5.1 தட வெளியீடுக்கு, &quot;4&quot; AC3 வெளியீடுக்கு.</longdesc>
					</local_schema>
				</entry>
				<entry name="debug">
					<local_schema short_desc="மீட்டிசைக்கும் இயந்திரத்தை வழு நீக்கத்துக்கு இயலுமை படுத்த வேண்டுமா?">
					</local_schema>
				</entry>
				<entry name="deinterlace">
					<local_schema short_desc="டீஇன்டர்லேஸிங்கை செயல்படச்செய்">
					</local_schema>
				</entry>
				<entry name="shuffle">
					<local_schema short_desc="கலக்கும் பாங்கு">
					</local_schema>
				</entry>
				<entry name="repeat">
					<local_schema short_desc="மீட்டுஇயக்கும் வகை">
					</local_schema>
				</entry>
				<entry name="connection_speed">
					<local_schema short_desc="வலையமைப்பு இணைப்பு வேகம்">
						<longdesc>தோராயமான வலை பின்னல் வேகம். வலைப்பின்னலில் உள்ள ஊடகத்தின் துல்லியத்தை தேர்ந்து எடுக்க உதவுகிறது.: &quot;0&quot; க்கு  14.4 கேபிபிஎஸ் மோடம் , &quot;1&quot; க்கு  19.2 கேபிபிஎஸ் மோடம் , &quot;2&quot; க்கு  28.8 கேபிபிஎஸ் மோடம் , &quot;3&quot; க்கு  33.6 கேபிபிஎஸ் மோடம் , &quot;4&quot; க்கு  34.4 கேபிபிஎஸ் மோடம் , &quot;5&quot; க்கு  56 கேபிபிஎஸ் மோடம் /ஐஎஸ்டிஎன், &quot;6&quot; க்கு  112 கேபிபிஎஸ் இரட்டை  ஐஎஸ்டிஎன்/டிஎஸ்எல் , &quot;7&quot; க்கு  256 கேபிபிஎஸ் டிஎஸ்எல் /கம்பி , &quot;8&quot; க்கு  384 கேபிபிஎஸ் டிஎஸ்எல் /கம்பி , &quot;9&quot; க்கு  512 கேபிபிஎஸ் டிஎஸ்எல் /கம்பி , &quot;10&quot; க்கு  1.5 எம்பிபிஎஸ் (Mbps)  T1/இன்ட்ராநெட்/லான் , &quot;11&quot; க்கு  இன்ட்ராநெட்/லான் .</longdesc>
					</local_schema>
				</entry>
				<entry name="auto_resize">
					<local_schema short_desc="கோப்பு ஏற்றப்படும் போது தானியங்கியாக திரையை மறு அளவாக்கு.">
					</local_schema>
				</entry>
				<entry name="saturation">
					<local_schema short_desc="விடியோவின் ஒளி தெவிட்டம்.">
					</local_schema>
				</entry>
				<entry name="hue">
					<local_schema short_desc="விடியோவின் ஒளி வண்ணச்சாயல்">
					</local_schema>
				</entry>
				<entry name="contrast">
					<local_schema short_desc="விடியோவின் ஒளி மாறுபாடு">
					</local_schema>
				</entry>
				<entry name="brightness">
					<local_schema short_desc="விடியோவின் பிரகாசம்.">
					</local_schema>
				</entry>
				<entry name="visual">
					<local_schema short_desc="காட்சி ஜாலம் சொருகிகளின் பெயர்">
					</local_schema>
				</entry>
				<entry name="show_vfx">
					<local_schema short_desc="விடியோ ஏதும் காட்டாதபோது காட்சி ஜாலங்களை காட்டு">
						<longdesc>ஒலி மட்டும் கோப்புகளை இயக்கும் போது காட்சி ஜாலங்களை காட்டு</longdesc>
					</local_schema>
				</entry>
				<entry name="lock_screensaver_on_audio">
					<local_schema short_desc="ஒலி மட்டும் பாடும்போது திரை சேமிப்பியை செயல்பட அனுமதி">
						<longdesc>ஒலி மட்டும் இயங்கும் போது கூட திரை சேமிப்பி துவங்க அனுமதி. இது திரையிலிருந்து சக்தி பெறும் ஒலிப்பான்களுக்கு பயனாகும்.</longdesc>
					</local_schema>
				</entry>
			</dir>
			<dir name="pointer-capture">
				<entry name="release_mod_ctrl">
					<local_schema short_desc="கண்ட்ரோல் விசையை அழுத்தினால் மட்டும் சுட்டியை விடவும்">
						<longdesc>பிடிப்பு பரப்பில் இருந்து சுட்டி விடுபட சொடுக்கி பொத்தான் &quot;release_button&quot; இல் உள்ளபோது கன்ட்ரோல் விசையை அழுத்த வேண்டுமா.</longdesc>
					</local_schema>
				</entry>
				<entry name="release_mod_alt">
					<local_schema short_desc="ஆல்ட் விசையை அழுத்தினால் மட்டும் சுட்டியை விடவும்">
						<longdesc>பிடிப்பு பரப்பில் இருந்து சுட்டி விடுபட சொடுக்கி பொத்தான் &quot;release_button&quot; இல் உள்ளபோது ஆல்ட் விசையை அழுத்த வேண்டுமா.</longdesc>
					</local_schema>
				</entry>
				<entry name="release_mod_shift">
					<local_schema short_desc="ஷிஃப்ட் விசையை அழுத்தினால் மட்டும் சுட்டியை விடவும்">
						<longdesc>பிடிப்பு பரப்பில் இருந்து சுட்டி விடுபட சொடுக்கி பொத்தான் &quot;release_button&quot; இல் உள்ளபோது ஷிப்ட் விசையை அழுத்த வேண்டுமா.</longdesc>
					</local_schema>
				</entry>
				<entry name="capture_mod_ctrl">
					<local_schema short_desc="கண்ட்ரோல் விசையை அழுத்தினால் மட்டும் சுட்டியை பிடிக்கவும்">
						<longdesc>பிடிப்பு பரப்பில் உள்ளபோது சுட்டியை பிடிக்க கன்ட்ரோல் விசையை அழுத்த வேண்டுமா. இந்த தேர்வு உண்மை என அமைத்து, ஒரு சொடுக்கி பொத்தானையும் &quot;capture_button&quot; விசையில் அமைத்து இருந்தால் பின் கன்ட்ரோல் விசையை சொடுக்கி விசையுடன் அழுத்த வேண்டும்.</longdesc>
					</local_schema>
				</entry>
				<entry name="capture_mod_alt">
					<local_schema short_desc="ஆல்ட் விசையை அழுத்தினால் மட்டும் சுட்டியை பிடிக்கவும்">
						<longdesc>பிடிப்பு பரப்பில் உள்ளபோது சுட்டியை பிடிக்க ஆல்ட் விசையை அழுத்த வேண்டுமா. இந்த தேர்வு உண்மை என அமைத்து, ஒரு சொடுக்கி பொத்தானையும் &quot;capture_button&quot; விசையில் அமைத்து இருந்தால் பின் ஆல்ட் விசையை சொடுக்கி விசையுடன் அழுத்த வேண்டும்.</longdesc>
					</local_schema>
				</entry>
				<entry name="capture_mod_shift">
					<local_schema short_desc="ஷிஃப்ட் விசையை அழுத்தினால் மட்டும் சுட்டியை பிடிக்கவும்">
						<longdesc>பிடிப்பு பரப்பில் உள்ளபோது சுட்டியை பிடிக்க ஷிப்ட் விசையை அழுத்த வேண்டுமா. இந்த தேர்வு உண்மை என அமைத்து, ஒரு சொடுக்கி பொத்தானையும் &quot;capture_button&quot; விசையில் அமைத்து இருந்தால் பின் ஷிப்ட் விசையை சொடுக்கி விசையுடன் அழுத்த வேண்டும்.</longdesc>
					</local_schema>
				</entry>
				<entry name="release_button">
					<local_schema short_desc="சுட்டியை விட பயன்பட்ட சொடுக்கி பொத்தான் ">
						<longdesc>பிடிப்பு பரப்பில் இருந்து சுட்டியை விட இந்த சொடுக்கி விசையை அழுத்த வேண்டும். செல்லுபடியாகும் மதிப்புகள்: &quot;1&quot; க்கு இடது பொத்தான், &quot;2&quot; க்கு நடு பொத்தான், மற்றும்  &quot;3&quot; க்கு இடது பொத்தான்.</longdesc>
					</local_schema>
				</entry>
				<entry name="capture_button">
					<local_schema short_desc="சுட்டியை பிடிக்க பயன்பட்ட சொடுக்கி பொத்தான் ">
						<longdesc>பிடிப்பு பரப்பில் இருக்கும்போது சுட்டியை பிடிக்க இந்த சொடுக்கி விசையை அழுத்த வேண்டும். செல்லுபடியாகும் மதிப்புகள்:&quot;0&quot; எனில் ஒரு பொத்தானும் தேவையில்லை, &quot;1&quot; க்கு இடது பொத்தான், &quot;2&quot; க்கு நடு பொத்தான், மற்றும்  &quot;3&quot; க்கு இடது பொத்தான்.</longdesc>
					</local_schema>
				</entry>
				<entry name="size">
					<local_schema short_desc="பிடிப்பு பரப்பின் அளவு ">
						<longdesc>பிடிப்பு பரப்பின் அகலம் பிக்ஸல்களில்.</longdesc>
					</local_schema>
				</entry>
			</dir>
		</dir>
	</dir>
</gconf>
